{
  "lastGenerated": "2026-04-14T05:51:43.930Z",
  "posts": [
    {
      "id": "nazca-lines-gigantic-geoglyphs-peru-desert",
      "title": "The Nazca Lines: Gigantic Geoglyphs Etched into Peru's Desert Floor",
      "category": "discoveries",
      "imageUrl": "https://images.unsplash.com/photo-1655491378664-1d054f1c46a3?crop=entropy&cs=tinysrgb&fit=max&fm=jpg&ixid=M3w5MTg2MDZ8MHwxfHJhbmRvbXx8fHx8fHx8fDE3NzYxNDA2MDN8&ixlib=rb-4.1.0&q=80&w=1080",
      "productUrl": "https://surfaced-x.pages.dev/discoveries/nazca-lines-gigantic-geoglyphs-peru-desert",
      "affiliateUrl": "https://surfaced-x.pages.dev/discoveries/nazca-lines-gigantic-geoglyphs-peru-desert",
      "platforms": {
        "pinterest": {
          "boardName": "New Discoveries"
        }
      },
      "status": "failed",
      "generatedAt": "2026-04-14T05:51:42.428Z",
      "publishedAt": "2026-04-14T05:51:44.300Z",
      "publishResults": {
        "bluesky": false,
        "pinterest": false,
        "twitter": false
      }
    },
    {
      "id": "marvelous-mimic-octopus-master-disguise",
      "title": "The Marvelous Mimic Octopus: A Master of Disguise Impersonating Multiple Sea Creatures",
      "category": "discoveries",
      "imageUrl": "https://images.unsplash.com/photo-1624772155811-1516de8dacad?crop=entropy&cs=tinysrgb&fit=max&fm=jpg&ixid=M3w5MTg2MDZ8MHwxfHJhbmRvbXx8fHx8fHx8fDE3NzYxNDA2MDZ8&ixlib=rb-4.1.0&q=80&w=1080",
      "productUrl": "https://surfaced-x.pages.dev/discoveries/marvelous-mimic-octopus-master-disguise",
      "affiliateUrl": "https://surfaced-x.pages.dev/discoveries/marvelous-mimic-octopus-master-disguise",
      "platforms": {
        "pinterest": {
          "boardName": "New Discoveries"
        }
      },
      "status": "failed",
      "generatedAt": "2026-04-14T05:51:43.930Z",
      "publishedAt": "2026-04-14T05:51:44.301Z",
      "publishResults": {
        "bluesky": false,
        "pinterest": false,
        "twitter": false
      }
    }
  ]
}